ezhook/__init__.py
ezhook-0.0.2.dist-info/LICENSE
ezhook-0.0.2.dist-info/METADATA
ezhook-0.0.2.dist-info/WHEEL
ezhook-0.0.2.dist-info/top_level.txt
ezhook-0.0.2.dist-info/RECORD
