Metadata-Version: 2.1
Name: ezhook
Version: 0.0.2
Summary: Send discord webhooks in python with 2 lines of code!
Home-page: https://rjson.dev/
Author: RJSON LABS
License: UNKNOWN
Platform: UNKNOWN
Classifier: Programming Language :: Python :: 3
Classifier: License :: OSI Approved :: MIT License
Classifier: Operating System :: OS Independent
Requires-Python: >=3.6
Requires-Dist: aiohttp
Requires-Dist: discord.py
